{"cameraMode":{"drawMode":0,"name":"Shaded","section":"Shading Mode"},"sceneLighting":true,"audioPlay":false,"sceneViewState":{"m_AlwaysRefresh":false,"showFog":true,"showSkybox":true,"showFlares":true,"showImageEffects":true,"showParticleSystems":true,"showVisualEffectGraphs":true,"m_FxEnabled":true},"in2DMode":false,"pivot":{"x":5.811161041259766,"y":4.427088260650635,"z":-5.6472086906433109},"rotation":{"x":-0.0553443506360054,"y":0.7294802069664002,"z":-0.05944596230983734,"w":-0.6791714429855347},"size":1.1489125490188599,"orthographic":false}